LICENSE
README.md
setup.cfg
setup.py
npeb/GLMixture.py
npeb/Grenander.py
npeb/PMixture.py
npeb/__init__.py
npeb.egg-info/PKG-INFO
npeb.egg-info/SOURCES.txt
npeb.egg-info/dependency_links.txt
npeb.egg-info/requires.txt
npeb.egg-info/top_level.txt