Metadata-Version: 2.1
Name: npeb
Version: 0.0.1
Summary: Nonparametric Empirical Bayes
Home-page: https://github.com/jake-soloff/NPEB
Download-URL: https://github.com/jake-soloff/NPEB/archive/refs/tags/v_001.tar.gz
Author: Jake A. Soloff
Author-email: jakesoloff@gmail.com
License: MIT
Keywords: Empirical Bayes,NPMLE,Mixture models
Classifier: Development Status :: 3 - Alpha
Classifier: Intended Audience :: Science/Research
Classifier: Intended Audience :: Developers
Classifier: Topic :: Software Development :: Build Tools
Classifier: License :: OSI Approved :: MIT License
Classifier: Programming Language :: Python :: 3
Classifier: Programming Language :: Python :: 3.4
Classifier: Programming Language :: Python :: 3.5
Classifier: Programming Language :: Python :: 3.6
Classifier: Programming Language :: Python :: 3.7
Classifier: Programming Language :: Python :: 3.8
Classifier: Programming Language :: Python :: 3.9
Classifier: Programming Language :: Python :: 3.10
Classifier: Programming Language :: Python :: 3.11
License-File: LICENSE
Requires-Dist: numpy
Requires-Dist: scipy
Requires-Dist: sklearn
Requires-Dist: pandas
